{
  "above_pivot": false,
  "adr_pct": 2.080179015934249,
  "contraction_score_raw": 0.0,
  "distance_52w_high_pct": -1.4096244663588609,
  "distance_pivot_pct": -1.6000050511853492,
  "dollar_volume_20d": 43978482.701911926,
  "entry_policy_version": "1.0.1",
  "entry_rank_pct": 90.6392694063927,
  "estimate_revision": null,
  "extension_atr": 4.42601767976425,
  "generated_at": "2026-07-22T13:36:34.167024Z",
  "hard_block": false,
  "industry": null,
  "industry_rank_pct": null,
  "institutional": null,
  "leader_policy_version": "1.0.1",
  "leader_rank_pct": 95.57077625570777,
  "market_cap": 3608521132.0,
  "market_policy_version": "1.0.1",
  "narrative": null,
  "near_ema21_low": false,
  "participation_score_raw": 0.6577785792126948,
  "pct_contraction_score_raw": 25.570776255707763,
  "pct_distance_52w_high_pct": 90.41095890410958,
  "pct_dollar_volume_20d": 32.009132420091326,
  "pct_extension_atr_quality": 3.7649219467401287,
  "pct_participation_score_raw": 95.93607305936072,
  "pct_pivot_quality_raw": 90.0,
  "pct_reward_risk_raw": 16.897506925207757,
  "pct_rs_change_raw_126": 88.66697631212263,
  "pct_rs_change_raw_189": 94.61610486891385,
  "pct_rs_change_raw_63": 70.92754960775265,
  "pct_rs_raw_126": 83.52668213457076,
  "pct_rs_raw_189": 85.0140056022409,
  "pct_rs_raw_21": 86.43835616438355,
  "pct_rs_raw_252": 75.01178689297501,
  "pct_rs_raw_63": 84.22263109475621,
  "pct_stop_risk_pct_quality": 17.671232876712327,
  "pct_story_acceleration_raw": null,
  "pct_story_dilution_quality_raw": null,
  "pct_story_growth_raw": null,
  "pct_story_quality_raw": null,
  "pct_supply_risk_raw_quality": null,
  "pct_trend_alignment": 83.97260273972603,
  "pct_volume_ratio_20d": 95.93607305936072,
  "pivot_20d": 36.25,
  "pivot_quality_raw": 0.8399994948814651,
  "price": 35.66999816894531,
  "reward_risk_raw": 0.6107822292313281,
  "rs_change_raw_126": 0.22166700964522446,
  "rs_change_raw_189": 0.3785216111946148,
  "rs_change_raw_21": 0.15820515664480328,
  "rs_change_raw_252": 0.2044164072460095,
  "rs_change_raw_63": 0.17250218886702795,
  "rs_raw_126": 0.21767995406731955,
  "rs_raw_189": 0.3898751745170903,
  "rs_raw_21": 0.17012282857929018,
  "rs_raw_252": 0.2192001548153839,
  "rs_raw_63": 0.11473460562216187,
  "schema_version": "1.0",
  "score_breakout": 88.54147718803206,
  "score_candidate": 79.37339804073622,
  "score_compounder": 83.90943839432897,
  "score_confidence": 0.6,
  "score_emerging": 82.3696227732602,
  "score_entry": 59.210042608919494,
  "score_entry_confidence": 1.0,
  "score_entry_risk": 13.308061679130658,
  "score_entry_technical": 72.97488584474885,
  "score_fundamental": null,
  "score_improvement": 81.68526027500741,
  "score_leader": 75.53494377463106,
  "score_leader_confidence": 1.0,
  "score_leadership": 61.14155251141551,
  "score_momentum": 83.90943839432897,
  "score_policy_version": "1.0.1",
  "score_quality": null,
  "score_story": null,
  "score_story_confidence": 0.0,
  "score_theme": 0.436132,
  "score_turnaround": 82.13009589887172,
  "sector": "金融",
  "sector_rank_pct": 61.14155251141552,
  "setup": "EXTENDED",
  "shares_yoy": null,
  "sma10": 34.83499984741211,
  "sma150": 29.20165097554525,
  "sma200": 27.91151382446289,
  "sma50": 32.1291849899292,
  "stop_ema21_low": 33.75957541632245,
  "stop_risk_pct": 2.3408981339958816,
  "stop_sma10": 34.83499984741211,
  "story_acceleration_raw": null,
  "story_dilution_quality_raw": null,
  "story_growth_raw": null,
  "story_phase": "MIXED",
  "story_policy_version": "1.0.2",
  "story_quality_raw": null,
  "story_rank_pct": null,
  "supply_risk_raw": null,
  "theme": "金融",
  "theme_phase": "MIXED",
  "theme_policy_version": "1.0.1",
  "ticker": "FFBC",
  "trend_alignment": 1.0,
  "volume_ratio_20d": 1.3155571584253896
}